pygp
