Metadata-Version: 1.1
Name: pygp
Version: 1.1.10
Summary: 
